ssl_metrics_badges/__init__.py
ssl_metrics_badges/main.py
ssl_metrics_badges/version.py
ssl_metrics_badges-0.2.1.dist-info/LICENSE
ssl_metrics_badges-0.2.1.dist-info/METADATA
ssl_metrics_badges-0.2.1.dist-info/WHEEL
ssl_metrics_badges-0.2.1.dist-info/entry_points.txt
ssl_metrics_badges-0.2.1.dist-info/top_level.txt
ssl_metrics_badges-0.2.1.dist-info/RECORD
