Metadata-Version: 2.1
Name: ssl-metrics-badges
Version: 0.2.1
Summary: SSL Metrics Badges - Custom SVG Metric Badges
Home-page: https://ssl.cs.luc.edu/projects/metricsDashboard
Author: Software and Systems Laboratory - Loyola University Chicago
Author-email: ssl-metrics@ssl.luc.edu
License: BSD
Project-URL: Bug Tracker, https://github.com/SoftwareSystemsLaboratory/ssl-metrics-badges/issues
Project-URL: GitHub Repository, https://github.com/SoftwareSystemsLaboratory/ssl-metrics-badges
Keywords: bus factor,commits,engineering,git,github,issue density,issues,kloc,loyola,loyola university chicago,luc,mining,metrics,repository,repository mining,simple,software,software engineering,software metrics,software systems laboratory,ssl
Platform: UNKNOWN
Classifier: Development Status :: 4 - Beta
Classifier: Intended Audience :: Science/Research
Classifier: Intended Audience :: Developers
Classifier: License :: OSI Approved :: BSD License
Classifier: Programming Language :: Python
Classifier: Programming Language :: Python :: 3
Classifier: Programming Language :: Python :: 3.9
Classifier: Programming Language :: Python :: 3 :: Only
Classifier: Topic :: Software Development
Classifier: Topic :: Scientific/Engineering
Classifier: Operating System :: POSIX
Classifier: Operating System :: Unix
Classifier: Operating System :: MacOS
Requires-Python: >=3.9
License-File: LICENSE
Requires-Dist: pybadges (>=2.2.1)
